multiplicationMatrix_Tese.py
multiplicationMatrix_Tese-0.0.3.dist-info/LICENSE.txt
multiplicationMatrix_Tese-0.0.3.dist-info/METADATA
multiplicationMatrix_Tese-0.0.3.dist-info/WHEEL
multiplicationMatrix_Tese-0.0.3.dist-info/top_level.txt
multiplicationMatrix_Tese-0.0.3.dist-info/RECORD
