Metadata-Version: 2.1
Name: multiplicationMatrix-Tese
Version: 0.0.3
Summary: Basic multuplication!
Home-page: UNKNOWN
Author: Joao Rodrigues
Author-email: joao_manuel1999@hotmail.com
License: UNKNOWN
Platform: UNKNOWN
Classifier: Programming Language :: Python :: 3.10
Classifier: Operating System :: Microsoft :: Windows
Classifier: Environment :: GPU :: NVIDIA CUDA :: 11.2
License-File: LICENSE.txt
Requires-Dist: numpy
Requires-Dist: scipy
Requires-Dist: cupy-cuda112
